<annotation>
	<folder>2</folder>
	<filename>209.jpg</filename>
	<path>D:\PhD\MISSION\MISSION - 3 Autmated Damage Detection\Data\Defect Dataset\2\209.jpg</path>
	<source>
		<database>Unknown</database>
	</source>
	<size>
		<width>800</width>
		<height>600</height>
		<depth>3</depth>
	</size>
	<segmented>0</segmented>
	<object>
		<name>Crack</name>
		<pose>Unspecified</pose>
		<truncated>0</truncated>
		<difficult>0</difficult>
		<bndbox>
			<xmin>272</xmin>
			<ymin>272</ymin>
			<xmax>434</xmax>
			<ymax>316</ymax>
		</bndbox>
	</object>
	<object>
		<name>Spalling</name>
		<pose>Unspecified</pose>
		<truncated>0</truncated>
		<difficult>0</difficult>
		<bndbox>
			<xmin>493</xmin>
			<ymin>265</ymin>
			<xmax>674</xmax>
			<ymax>347</ymax>
		</bndbox>
	</object>
</annotation>
